Metadata-Version: 2.4
Name: ps3-python
Version: 0.1.0
Summary: Scaling Vision Pre-Training to 4K Resolution
Author-email: Baifeng Shi <baifeng_shi@berkeley.edu>
License: Apache 2.0
Project-URL: Homepage, https://nvlabs.github.io/PS3
Project-URL: Code, https://github.com/NVlabs/PS3
Classifier: Programming Language :: Python :: 3
Classifier: License :: OSI Approved :: Apache Software License
Requires-Python: >=3.8
License-File: LICENSE.md
Requires-Dist: torch
Requires-Dist: torchvision
Requires-Dist: transformers[sentencepiece]
Requires-Dist: timm>=1.0.15
Requires-Dist: einops
Requires-Dist: accelerate
Requires-Dist: pillow
Requires-Dist: tiktoken
Dynamic: license-file
